<?xml version="1.0" encoding="us-ascii"?>
<Catalog>
    <CSound id="Doodad_SpacePlatformSign_SuperNova" parent="Ambience_Object">
        <AssetArray>
            <File value="Assets\Music\Music_Club_LostViking_Boss_Loop.wav"/>
            <LoopCount value="-1"/>
            <Pitch value="-12.000000,-12.000000"/>
            <FacialGroup value=""/>
        </AssetArray>
        <AssetArray>
            <File value="Assets\Music\Music_Club_LostViking_Game1_Loop.wav"/>
            <LoopCount value="-1"/>
            <Pitch value="-1.000000,-1.000000"/>
            <FacialGroup value=""/>
        </AssetArray>
        <AssetArray File="Assets\Music\Music_Club_LostViking_Game2_Loop.wav" LoopCount="-1" FacialGroup=""/>
        <AssetArray>
            <File value="Assets\Music\Music_Club_MuleParty2_Loop.wav"/>
            <LoopCount value="-1"/>
            <Pitch value="-2.000000,-2.000000"/>
            <FacialGroup value=""/>
        </AssetArray>
        <AssetArray>
            <File value="Assets\Music\Music_Club_PsiOps_Loop.wav"/>
            <LoopCount value="-1"/>
            <Pitch value="-1.000000,-1.000000"/>
            <FacialGroup value=""/>
        </AssetArray>
        <DupeMuteCount value="2"/>
        <VolumeRolloffPoints Distance="5.000000"/>
        <VolumeRolloffPoints Distance="9.000000" Volume="-19.000000"/>
        <VolumeRolloffPoints Distance="12.000000" Volume="-96.000000"/>
        <Spread value="30.000000"/>
        <Volume value="-2.000000,-2.000000"/>
    </CSound>
</Catalog>
